{
  "configVersion": 1,
  "timestamp": 1767713807906,
  "index": "/index.html",
  "assetGroups": [
    {
      "name": "app",
      "installMode": "prefetch",
      "updateMode": "prefetch",
      "cacheQueryOptions": {
        "ignoreVary": true
      },
      "urls": [
        "/310.7e31f5987f528a9c.js",
        "/315.0b85a0b2aaf4469c.js",
        "/347.225436218c85011f.js",
        "/index.html",
        "/main.600fecf1f0fc99e4.js",
        "/manifest.webmanifest",
        "/polyfills.44a068f0fc8ac738.js",
        "/runtime.efcb207202e234bf.js",
        "/styles.2e19c1028b225363.css"
      ],
      "patterns": []
    },
    {
      "name": "assets",
      "installMode": "lazy",
      "updateMode": "prefetch",
      "cacheQueryOptions": {
        "ignoreVary": true
      },
      "urls": [
        "/assets/android-chrome-192x192.png",
        "/assets/android-chrome-512x512.png",
        "/assets/apple-touch-icon.png",
        "/assets/audios/bell.mp3",
        "/assets/favicon-16x16.png",
        "/assets/favicon-32x32.png",
        "/assets/favicon.ico"
      ],
      "patterns": []
    }
  ],
  "dataGroups": [
    {
      "name": "api-cache",
      "patterns": [
        "https:\\/\\/cdnjs\\.cloudflare\\.com\\/.*",
        "https:\\/\\/fonts\\.googleapis\\.com\\/.*",
        "https:\\/\\/fonts\\.gstatic\\.com\\/.*"
      ],
      "strategy": "cache",
      "maxSize": 100,
      "maxAge": 2592000000,
      "cacheQueryOptions": {
        "ignoreVary": true
      },
      "version": 1
    }
  ],
  "hashTable": {
    "/310.7e31f5987f528a9c.js": "130087d0e4db96f6d3588e9c2c035fff416f3c81",
    "/315.0b85a0b2aaf4469c.js": "7c32d84819e1ba69dd325e1429879058734e82ae",
    "/347.225436218c85011f.js": "29212853241a5085243668fc7602f133701f3877",
    "/assets/android-chrome-192x192.png": "6773e500991f0820cc9ded5b10f810a90a098d0e",
    "/assets/android-chrome-512x512.png": "660a32406a4f87f738be26d528ec1afe9af5ded5",
    "/assets/apple-touch-icon.png": "c59de3e238dd74094969c2f85046014b8660722f",
    "/assets/audios/bell.mp3": "dc7ec0b0fa62567eba20eb65e12b0fae0252c9a2",
    "/assets/favicon-16x16.png": "29d06d49caaeff848b7e15ab52014ff4ca457cf0",
    "/assets/favicon-32x32.png": "188ed7f70759683bc12adbe51a9534dd5e55b8e8",
    "/assets/favicon.ico": "ee9ea68ae70414768728ee467e46f0cb44950e34",
    "/index.html": "2bacb0cef13e5d71b0da173354390f6d8e17531b",
    "/main.600fecf1f0fc99e4.js": "f23d0904f65abd8c2da432c4009da0fc2aa13793",
    "/manifest.webmanifest": "f60b065209a2121943a23ac8045706e2e98b20c8",
    "/polyfills.44a068f0fc8ac738.js": "30326e4fb9ce57713dc3feab5cf8004f6ef15626",
    "/runtime.efcb207202e234bf.js": "843f5375817d733e4e88c2e2a65d813267f6977a",
    "/styles.2e19c1028b225363.css": "6b10596b48bd0a45daa9f3497e08ab92de59930c"
  },
  "navigationUrls": [
    {
      "positive": false,
      "regex": "^\\/(?:.+\\/)?[^/]*\\.[^/]*$"
    },
    {
      "positive": true,
      "regex": "^\\/.*$"
    }
  ],
  "navigationRequestStrategy": "performance"
}